<?xml version="1.0" encoding="UTF-8"?>
<feature
      id="de.bsvrz.buv.vew.feature"
      label="%featureName"
      version="2.0.0.qualifier"
      provider-name="%featureProvider">

   <description>
      %descriptionText
   </description>

   <copyright>
      %copyrightText
   </copyright>

   <license url="http://www.gnu.org/licenses/gpl-2.0.html">
      %licenseText
   </license>

   <requires>
      <import feature="org.eclipse.fx.runtime.min.feature" version="3.0.0.201705220748"/>
   </requires>

   <plugin
         id="de.bsvrz.vew.syskal"
         download-size="0"
         install-size="0"
         version="0.0.0"
         unpack="false"/>

   <plugin
         id="org.eclipse.fx.javafx"
         download-size="0"
         install-size="0"
         version="0.0.0"
         unpack="false"/>

</feature>
